pypgrest/__init__.py
pypgrest/pypgrest.py
pypgrest_dev-0.2.0.dist-info/METADATA
pypgrest_dev-0.2.0.dist-info/WHEEL
pypgrest_dev-0.2.0.dist-info/top_level.txt
pypgrest_dev-0.2.0.dist-info/RECORD
