Metadata-Version: 2.1
Name: pypgrest-dev
Version: 0.2.0
Summary: A Python API client for interacting with PostgREST applications.
Home-page: http://github.com/cityofaustin/pypgrest
Author: John Clary
Author-email: transportation.data@austintexas.gov
License: Public Domain
Keywords: postgres postgrest api api-client integration python
Classifier: Development Status :: 4 - Beta
Classifier: Intended Audience :: Developers
Classifier: License :: Public Domain
Classifier: Programming Language :: Python :: 3
Requires-Dist: requests
